twiter/__init__.py
twiter/__main__.py
Titter-1.dist-info/METADATA
Titter-1.dist-info/WHEEL
Titter-1.dist-info/top_level.txt
Titter-1.dist-info/RECORD
