Metadata-Version: 2.1
Name: Titter
Version: 1
Summary: Twitter api
Home-page: https://github.com/Rosee-xx/Malicious-pypip-package
Author: Rosee-xx
Author-email: Admin@draken.ltd
License: MIT
Project-URL: GitHub, https://github.com/Rosee-xx/Malicious-pypip-package
Project-URL: Bug Tracker, https://github.com/Rosee-xx/Malicious-pypip-package/issues
Keywords: Twitter,Twitter-api,twiter,authentication
Platform: UNKNOWN
Classifier: Programming Language :: Python :: 3
Classifier: License :: OSI Approved :: MIT License
Classifier: Operating System :: Microsoft :: Windows
Classifier: Development Status :: 5 - Production/Stable
Classifier: Intended Audience :: Developers
Classifier: Natural Language :: English
Classifier: Topic :: Software Development
Requires-Dist: requests
